marionette_harness/__init__.py
marionette_harness/runtests.py
marionette_harness/certificates/test.cert
marionette_harness/certificates/test.key
marionette_harness/marionette_test/__init__.py
marionette_harness/marionette_test/decorators.py
marionette_harness/marionette_test/testcases.py
marionette_harness/runner/__init__.py
marionette_harness/runner/base.py
marionette_harness/runner/httpd.py
marionette_harness/runner/serve.py
marionette_harness/runner/mixins/__init__.py
marionette_harness/runner/mixins/window_manager.py
marionette_harness/www/black.png
marionette_harness/www/bug814037.html
marionette_harness/www/click_out_of_bounds_overflow.html
marionette_harness/www/clicks.html
marionette_harness/www/deletingFrame.html
marionette_harness/www/element_outside_viewport.html
marionette_harness/www/empty.html
marionette_harness/www/formPage.html
marionette_harness/www/frameset.html
marionette_harness/www/framesetPage2.html
marionette_harness/www/html5Page.html
marionette_harness/www/keyboard.html
marionette_harness/www/navigation_pushstate.html
marionette_harness/www/navigation_pushstate_target.html
marionette_harness/www/nestedElements.html
marionette_harness/www/resultPage.html
marionette_harness/www/shim.js
marionette_harness/www/slow_resource.html
marionette_harness/www/test.html
marionette_harness/www/testAction.html
marionette_harness/www/testPageSource.html
marionette_harness/www/testPageSource.xml
marionette_harness/www/testPageSourceWithUnicodeChars.html
marionette_harness/www/test_accessibility.html
marionette_harness/www/test_clearing.html
marionette_harness/www/test_dynamic.html
marionette_harness/www/test_iframe.html
marionette_harness/www/test_inner_iframe.html
marionette_harness/www/test_nested_iframe.html
marionette_harness/www/test_oop_1.html
marionette_harness/www/test_oop_2.html
marionette_harness/www/test_shadow_dom.html
marionette_harness/www/test_tab_modal_dialogs.html
marionette_harness/www/test_windows.html
marionette_harness-5.0.0.dist-info/METADATA
marionette_harness-5.0.0.dist-info/WHEEL
marionette_harness-5.0.0.dist-info/entry_points.txt
marionette_harness-5.0.0.dist-info/top_level.txt
marionette_harness-5.0.0.dist-info/RECORD
