Metadata-Version: 2.1
Name: marionette-harness
Version: 5.0.0
Summary: Marionette test automation harness
Home-page: https://wiki.mozilla.org/Auto-tools/Projects/Marionette
Author: Auto-tools
Author-email: tools-marionette@lists.mozilla.org
License: Mozilla Public License 2.0 (MPL 2.0)
Keywords: mozilla
Platform: UNKNOWN
Classifier: Development Status :: 5 - Production/Stable
Classifier: Intended Audience :: Developers
Classifier: License :: OSI Approved :: Mozilla Public License 2.0 (MPL 2.0)
Classifier: Operating System :: MacOS :: MacOS X
Classifier: Operating System :: Microsoft :: Windows
Classifier: Operating System :: POSIX
Classifier: Topic :: Software Development :: Quality Assurance
Classifier: Topic :: Software Development :: Testing
Classifier: Topic :: Utilities
Classifier: Programming Language :: Python
Classifier: Programming Language :: Python :: 2.7
Requires-Dist: browsermob-proxy (>=0.8.0)
Requires-Dist: manifestparser (>=1.1)
Requires-Dist: marionette-driver (>=3.0.0)
Requires-Dist: mozcrash (>=1.1.0)
Requires-Dist: mozdevice (>=3.0.1)
Requires-Dist: mozinfo (>=1.0.0)
Requires-Dist: mozlog (>=4.0)
Requires-Dist: moznetwork (>=0.27)
Requires-Dist: mozprocess (>=1.0.0)
Requires-Dist: mozprofile (>=2.2.0)
Requires-Dist: mozrunner (>=7.4.0)
Requires-Dist: moztest (>=0.8)
Requires-Dist: mozversion (>=2.1.0)
Requires-Dist: six
Requires-Dist: wptserve (>=2.0.0)
